processor/__init__.py
processor/comparison/__init__.py
processor/comparison/comparison_functions.py
processor/comparison/interpreter.py
processor/comparison/comparisonantlr/__init__.py
processor/comparison/comparisonantlr/comparatorLexer.py
processor/comparison/comparisonantlr/comparatorListener.py
processor/comparison/comparisonantlr/comparatorParser.py
processor/comparison/comparisonantlr/compare_types.py
processor/comparison/comparisonantlr/rule_interpreter.py
processor/comparison/comparisonantlr/test_comparator.py
processor/connector/__init__.py
processor/connector/snapshot.py
processor/connector/snapshot_aws.py
processor/connector/snapshot_azure.py
processor/connector/snapshot_custom.py
processor/connector/snapshot_google.py
processor/connector/snapshot_utils.py
processor/connector/validation.py
processor/connector/vault.py
processor/database/__init__.py
processor/database/database.py
processor/helper/__init__.py
processor/helper/config/__init__.py
processor/helper/config/config_utils.py
processor/helper/config/rundata_utils.py
processor/helper/file/__init__.py
processor/helper/file/file_utils.py
processor/helper/httpapi/__init__.py
processor/helper/httpapi/http_utils.py
processor/helper/httpapi/restapi.py
processor/helper/httpapi/restapi_azure.py
processor/helper/json/__init__.py
processor/helper/json/json_utils.py
processor/helper/utils/__init__.py
processor/helper/utils/cli_populate_json.py
processor/helper/utils/cli_terraform_to_json.py
processor/helper/utils/cli_validator.py
processor/logging/__init__.py
processor/logging/log_handler.py
processor/reporting/__init__.py
processor/reporting/json_output.py
danielalejandrohc-0.1.4.dist-info/LICENSE
danielalejandrohc-0.1.4.dist-info/METADATA
danielalejandrohc-0.1.4.dist-info/WHEEL
danielalejandrohc-0.1.4.dist-info/entry_points.txt
danielalejandrohc-0.1.4.dist-info/top_level.txt
danielalejandrohc-0.1.4.dist-info/RECORD
