Metadata-Version: 2.1
Name: danielalejandrohc
Version: 0.1.4
Summary: Prancer Basic
Home-page: https://github.com/prancer-io/cloud-validation-framework
Author: Farshid M/Ajey Khanapuri
Author-email: ajey.khanapuri@liquware.com
License: BSD
Platform: UNKNOWN
Classifier: Development Status :: 3 - Alpha
Classifier: Topic :: Software Development :: Libraries :: Application Frameworks
Classifier: Topic :: Software Development :: Libraries :: Python Modules
Classifier: License :: OSI Approved :: BSD License
Requires-Python: >=3.0
Requires-Dist: antlr4-python3-runtime (==4.7.1)
Requires-Dist: boto3 (==1.9.86)
Requires-Dist: GitPython (==2.1.11)
Requires-Dist: pymongo (==3.7.2)
Requires-Dist: pytest (==4.0.1)
Requires-Dist: pytest-cov (==2.6.0)
Requires-Dist: pytest-mock (==1.10.0)
Requires-Dist: python-dateutil (==2.7.5)
Requires-Dist: requests (==2.20.1)
Requires-Dist: ply (==3.10)
Requires-Dist: pyhcl (==0.3.10)
Requires-Dist: google-api-python-client (==1.7.8)
Requires-Dist: google-auth (==1.6.3)
Requires-Dist: google-auth-httplib2 (==0.0.3)
Requires-Dist: oauth2client (==4.1.3)
